{"stats":{"minecraft:mined":{"minecraft:grass":1,"minecraft:acacia_log":2},"minecraft:killed_by":{"minecraft:skeleton":1},"minecraft:crafted":{"minecraft:acacia_planks":8},"minecraft:custom":{"minecraft:time_since_rest":6012,"minecraft:open_chest":2,"minecraft:waystone_activated":1,"minecraft:crouch_one_cm":286,"minecraft:play_time":11818,"minecraft:sprint_one_cm":25092,"minecraft:walk_one_cm":9393,"minecraft:damage_taken":343,"minecraft:deaths":1,"minecraft:sneak_time":74,"minecraft:walk_under_water_one_cm":8437,"minecraft:aviate_one_cm":5279,"minecraft:jump":40,"minecraft:leave_game":6,"minecraft:time_since_death":5989,"minecraft:walk_on_water_one_cm":5011,"minecraft:total_world_time":11818,"minecraft:climb_one_cm":1324,"minecraft:swim_one_cm":8098,"minecraft:interact_with_crafting_table":1,"minecraft:fall_one_cm":627,"minecraft:fly_one_cm":5731},"minecraft:picked_up":{"minecraft:acacia_log":2}},"DataVersion":3465}